statechart/__init__.py
statechart/display.py
statechart/event.py
statechart/pseudostates.py
statechart/runtime.py
statechart/states.py
statechart/transitions.py
statechart-0.4.2.dist-info/AUTHORS.rst
statechart-0.4.2.dist-info/LICENSE
statechart-0.4.2.dist-info/METADATA
statechart-0.4.2.dist-info/WHEEL
statechart-0.4.2.dist-info/top_level.txt
statechart-0.4.2.dist-info/RECORD
