Metadata-Version: 2.1
Name: statechart
Version: 0.4.2
Summary: Python UML statechart framework
Home-page: https://github.com/leighmck/statechart
Author: Leigh McKenzie
Author-email: maccarav0@gmail.com
License: ISCL
Keywords: statechart
Platform: UNKNOWN
Classifier: Development Status :: 2 - Pre-Alpha
Classifier: Intended Audience :: Developers
Classifier: License :: OSI Approved :: ISC License (ISCL)
Classifier: Natural Language :: English
Classifier: Programming Language :: Python :: 3
Classifier: Programming Language :: Python :: 3.4
